SPI_slave/rtl/top.v
module slave(
	input wire clk,
	input wire rst_n,
	input wire mosi,
	input wire sck,
	input wire cs,
	output reg miso,
	output reg [7:0] data_out
);

reg [7:0] shift_reg;
reg [2:0] bit_cnt;

always @(posedge clk or negedge rst_n) begin
	if(!rst_n) begin
		miso <= 1'b0;
		data_out <= 8'h00;
		shift_reg <= 8'h00;
		bit_cnt <= 3'b0;
	end else if (cs == 0) begin
		if(sck) begin
			shift_reg <= {shift_reg[6:0], mosi};
			bit_cnt <= bit_cnt + 1'b1;
			if(bit_cnt == 7) begin
				data_out <= {shift_reg[6:0], mosi};
			end
		end
		miso <= shift_reg[7];
	end else begin
		miso <= 1'b0;
	end
end
endmodule

SPI_slave/tb/test_bench.v
`timescale 1ns/1ps
module test_bench;
	reg clk;
	reg rst_n;
	reg mosi;
	reg sck;
	reg cs;
	wire miso;
	wire [7:0] data_out;

	slave dut(
		.clk(clk),
		.rst_n(rst_n),
		.mosi(mosi),
		.sck(sck),
		.cs(cs),
		.miso(miso),
		.data_out(data_out)
	);

	task verify;
		input [7:0] byte;
		integer i;
		begin
			for (i = 7; i >= 0; i = i - 1) begin
				mosi = byte[i];
				@(posedge clk); 
				sck = 1;
				@(posedge clk);
				sck = 0;
			end
			@(posedge clk);
			if (data_out == byte) begin
				$display("----------------------------------------------------------------------------------------------------------------");
				$display("PASSED: Expected data_out 8'h%h, Got data_out 8'h%h", byte, data_out);
				$display("----------------------------------------------------------------------------------------------------------------");
			end else begin
				$display("----------------------------------------------------------------------------------------------------------------");
				$display("FAILED: Expected data_out 8'h%h, Got data_out 8'h%h", byte, data_out);
				$display("----------------------------------------------------------------------------------------------------------------");
			end
		end
	endtask

	initial begin
		clk = 0;
		forever #5 clk = ~clk;
	end

	initial begin
		$dumpfile("test_bench.vcd");
		$dumpvars(0, test_bench);

		$display("---------------------------------------------------------------------------------------------------------------------");
		$display("---------------------------------------TESTBENCH FOR SPI SLAVE-------------------------------------------------------");
		$display("---------------------------------------------------------------------------------------------------------------------");

		rst_n = 0;
		mosi = 0;
		sck = 0;
		cs = 1;
		repeat (10) @(posedge clk);
		if (data_out == 8'h00) begin
			$display("----------------------------------------------------------------------------------------------------------------");
			$display("PASSED: Expected data_out 8'h%h, Got data_out 8'h%h", 8'h00, data_out);
			$display("----------------------------------------------------------------------------------------------------------------");
		end else begin
			$display("----------------------------------------------------------------------------------------------------------------");
			$display("FAILED: Expected data_out 8'h%h, Got data_out 8'h%h", 8'h00, data_out);
			$display("----------------------------------------------------------------------------------------------------------------");
		end

		rst_n = 1;
		cs = 0;
		@(posedge clk);
		verify(8'haa);

		@(posedge clk);
		verify(8'h33);

		@(posedge clk);
		verify(8'h0f);

		@(posedge clk);
		verify(8'hff);

		@(posedge clk);
		verify(8'h55);

		@(posedge clk);
		verify(8'h77);

		@(posedge clk);
		verify(8'hcc);

		@(posedge clk);
		verify(8'h11);

		@(posedge clk);
		verify(8'h99);

		@(posedge clk);
		verify(8'h66);

		@(posedge clk);
		verify(8'hff);

		#100;
		$finish;
	end
endmodule

SPI_slave/sim/test_bench.vcd
$date
	Tue Jan 14 04:43:55 2025
$end
$version
	Icarus Verilog
$end
$timescale
	1ps
$end
$scope module test_bench $end
$var wire 1 ! miso $end
$var wire 8 " data_out [7:0] $end
$var reg 1 # clk $end
$var reg 1 $ cs $end
$var reg 1 % mosi $end
$var reg 1 & rst_n $end
$var reg 1 ' sck $end
$scope module dut $end
$var wire 1 # clk $end
$var wire 1 $ cs $end
$var wire 1 % mosi $end
$var wire 1 & rst_n $end
$var wire 1 ' sck $end
$var reg 3 ( bit_cnt [2:0] $end
$var reg 8 ) data_out [7:0] $end
$var reg 1 ! miso $end
$var reg 8 * shift_reg [7:0] $end
$upscope $end
$scope task verify $end
$var reg 8 + byte [7:0] $end
$var integer 32 , i [31:0] $end
$upscope $end
$upscope $end
$enddefinitions $end
$comment Show the parameter values. $end
$dumpall
$end
#0
$dumpvars
bx ,
bx +
b0 *
b0 )
b0 (
0'
0&
0%
1$
0#
b0 "
0!
$end
#5000
1#
#10000
0#
#15000
1#
#20000
0#
#25000
1#
#30000
0#
#35000
1#
#40000
0#
#45000
1#
#50000
0#
#55000
1#
#60000
0#
#65000
1#
#70000
0#
#75000
1#
#80000
0#
#85000
1#
#90000
0#
#95000
0$
1&
1#
#100000
0#
#105000
1%
b111 ,
b10101010 +
1#
#110000
0#
#115000
b1 (
b1 *
1'
1#
#120000
0#
#125000
0%
b110 ,
0'
1#
#130000
0#
#135000
b10 (
b10 *
1'
1#
#140000
0#
#145000
1%
b101 ,
0'
1#
#150000
0#
#155000
b11 (
b101 *
1'
1#
#160000
0#
#165000
0%
b100 ,
0'
1#
#170000
0#
#175000
b100 (
b1010 *
1'
1#
#180000
0#
#185000
1%
b11 ,
0'
1#
#190000
0#
#195000
b101 (
b10101 *
1'
1#
#200000
0#
#205000
0%
b10 ,
0'
1#
#210000
0#
#215000
b110 (
b101010 *
1'
1#
#220000
0#
#225000
1%
b1 ,
0'
1#
#230000
0#
#235000
b111 (
b1010101 *
1'
1#
#240000
0#
#245000
0%
b0 ,
0'
1#
#250000
0#
#255000
b10101010 "
b10101010 )
b0 (
b10101010 *
1'
1#
#260000
0#
#265000
1!
b11111111111111111111111111111111 ,
0'
1#
#270000
0#
#275000
1#
#280000
0#
#285000
b111 ,
b110011 +
1#
#290000
0#
#295000
b1 (
b1010100 *
1'
1#
#300000
0#
#305000
0!
b110 ,
0'
1#
#310000
0#
#315000
b10 (
b10101000 *
1'
1#
#320000
0#
#325000
1!
1%
b101 ,
0'
1#
#330000
0#
#335000
b11 (
b1010001 *
1'
1#
#340000
0#
#345000
0!
b100 ,
0'
1#
#350000
0#
#355000
b100 (
b10100011 *
1'
1#
#360000
0#
#365000
1!
0%
b11 ,
0'
1#
#370000
0#
#375000
b101 (
b1000110 *
1'
1#
#380000
0#
#385000
0!
b10 ,
0'
1#
#390000
0#
#395000
b110 (
b10001100 *
1'
1#
#400000
0#
#405000
1!
1%
b1 ,
0'
1#
#410000
0#
#415000
b111 (
b11001 *
1'
1#
#420000
0#
#425000
0!
b0 ,
0'
1#
#430000
0#
#435000
b110011 "
b110011 )
b0 (
b110011 *
1'
1#
#440000
0#
#445000
b11111111111111111111111111111111 ,
0'
1#
#450000
0#
#455000
1#
#460000
0#
#465000
0%
b111 ,
b1111 +
1#
#470000
0#
#475000
b1 (
b1100110 *
1'
1#
#480000
0#
#485000
b110 ,
0'
1#
#490000
0#
#495000
b10 (
b11001100 *
1'
1#
#500000
0#
#505000
1!
b101 ,
0'
1#
#510000
0#
#515000
b11 (
b10011000 *
1'
1#
#520000
0#
#525000
b100 ,
0'
1#
#530000
0#
#535000
b100 (
b110000 *
1'
1#
#540000
0#
#545000
0!
1%
b11 ,
0'
1#
#550000
0#
#555000
b101 (
b1100001 *
1'
1#
#560000
0#
#565000
b10 ,
0'
1#
#570000
0#
#575000
b110 (
b11000011 *
1'
1#
#580000
0#
#585000
1!
b1 ,
0'
1#
#590000
0#
#595000
b111 (
b10000111 *
1'
1#
#600000
0#
#605000
b0 ,
0'
1#
#610000
0#
#615000
b1111 "
b1111 )
b0 (
b1111 *
1'
1#
#620000
0#
#625000
0!
b11111111111111111111111111111111 ,
0'
1#
#630000
0#
#635000
1#
#640000
0#
#645000
b111 ,
b11111111 +
1#
#650000
0#
#655000
b1 (
b11111 *
1'
1#
#660000
0#
#665000
b110 ,
0'
1#
#670000
0#
#675000
b10 (
b111111 *
1'
1#
#680000
0#
#685000
b101 ,
0'
1#
#690000
0#
#695000
b11 (
b1111111 *
1'
1#
#700000
0#
#705000
b100 ,
0'
1#
#710000
0#
#715000
b100 (
b11111111 *
1'
1#
#720000
0#
#725000
1!
b11 ,
0'
1#
#730000
0#
#735000
b101 (
1'
1#
#740000
0#
#745000
b10 ,
0'
1#
#750000
0#
#755000
b110 (
1'
1#
#760000
0#
#765000
b1 ,
0'
1#
#770000
0#
#775000
b111 (
1'
1#
#780000
0#
#785000
b0 ,
0'
1#
#790000
0#
#795000
b11111111 "
b11111111 )
b0 (
1'
1#
#800000
0#
#805000
b11111111111111111111111111111111 ,
0'
1#
#810000
0#
#815000
1#
#820000
0#
#825000
0%
b111 ,
b1010101 +
1#
#830000
0#
#835000
b1 (
b11111110 *
1'
1#
#840000
0#
#845000
1%
b110 ,
0'
1#
#850000
0#
#855000
b10 (
b11111101 *
1'
1#
#860000
0#
#865000
0%
b101 ,
0'
1#
#870000
0#
#875000
b11 (
b11111010 *
1'
1#
#880000
0#
#885000
1%
b100 ,
0'
1#
#890000
0#
#895000
b100 (
b11110101 *
1'
1#
#900000
0#
#905000
0%
b11 ,
0'
1#
#910000
0#
#915000
b101 (
b11101010 *
1'
1#
#920000
0#
#925000
1%
b10 ,
0'
1#
#930000
0#
#935000
b110 (
b11010101 *
1'
1#
#940000
0#
#945000
0%
b1 ,
0'
1#
#950000
0#
#955000
b111 (
b10101010 *
1'
1#
#960000
0#
#965000
1%
b0 ,
0'
1#
#970000
0#
#975000
b1010101 "
b1010101 )
b0 (
b1010101 *
1'
1#
#980000
0#
#985000
0!
b11111111111111111111111111111111 ,
0'
1#
#990000
0#
#995000
1#
#1000000
0#
#1005000
0%
b111 ,
b1110111 +
1#
#1010000
0#
#1015000
b1 (
b10101010 *
1'
1#
#1020000
0#
#1025000
1!
1%
b110 ,
0'
1#
#1030000
0#
#1035000
b10 (
b1010101 *
1'
1#
#1040000
0#
#1045000
0!
b101 ,
0'
1#
#1050000
0#
#1055000
b11 (
b10101011 *
1'
1#
#1060000
0#
#1065000
1!
b100 ,
0'
1#
#1070000
0#
#1075000
b100 (
b1010111 *
1'
1#
#1080000
0#
#1085000
0!
0%
b11 ,
0'
1#
#1090000
0#
#1095000
b101 (
b10101110 *
1'
1#
#1100000
0#
#1105000
1!
1%
b10 ,
0'
1#
#1110000
0#
#1115000
b110 (
b1011101 *
1'
1#
#1120000
0#
#1125000
0!
b1 ,
0'
1#
#1130000
0#
#1135000
b111 (
b10111011 *
1'
1#
#1140000
0#
#1145000
1!
b0 ,
0'
1#
#1150000
0#
#1155000
b1110111 "
b1110111 )
b0 (
b1110111 *
1'
1#
#1160000
0#
#1165000
0!
b11111111111111111111111111111111 ,
0'
1#
#1170000
0#
#1175000
1#
#1180000
0#
#1185000
b111 ,
b11001100 +
1#
#1190000
0#
#1195000
b1 (
b11101111 *
1'
1#
#1200000
0#
#1205000
1!
b110 ,
0'
1#
#1210000
0#
#1215000
b10 (
b11011111 *
1'
1#
#1220000
0#
#1225000
0%
b101 ,
0'
1#
#1230000
0#
#1235000
b11 (
b10111110 *
1'
1#
#1240000
0#
#1245000
b100 ,
0'
1#
#1250000
0#
#1255000
b100 (
b1111100 *
1'
1#
#1260000
0#
#1265000
0!
1%
b11 ,
0'
1#
#1270000
0#
#1275000
b101 (
b11111001 *
1'
1#
#1280000
0#
#1285000
1!
b10 ,
0'
1#
#1290000
0#
#1295000
b110 (
b11110011 *
1'
1#
#1300000
0#
#1305000
0%
b1 ,
0'
1#
#1310000
0#
#1315000
b111 (
b11100110 *
1'
1#
#1320000
0#
#1325000
b0 ,
0'
1#
#1330000
0#
#1335000
b11001100 "
b11001100 )
b0 (
b11001100 *
1'
1#
#1340000
0#
#1345000
b11111111111111111111111111111111 ,
0'
1#
#1350000
0#
#1355000
1#
#1360000
0#
#1365000
b111 ,
b10001 +
1#
#1370000
0#
#1375000
b1 (
b10011000 *
1'
1#
#1380000
0#
#1385000
b110 ,
0'
1#
#1390000
0#
#1395000
b10 (
b110000 *
1'
1#
#1400000
0#
#1405000
0!
b101 ,
0'
1#
#1410000
0#
#1415000
b11 (
b1100000 *
1'
1#
#1420000
0#
#1425000
1%
b100 ,
0'
1#
#1430000
0#
#1435000
b100 (
b11000001 *
1'
1#
#1440000
0#
#1445000
1!
0%
b11 ,
0'
1#
#1450000
0#
#1455000
b101 (
b10000010 *
1'
1#
#1460000
0#
#1465000
b10 ,
0'
1#
#1470000
0#
#1475000
b110 (
b100 *
1'
1#
#1480000
0#
#1485000
0!
b1 ,
0'
1#
#1490000
0#
#1495000
b111 (
b1000 *
1'
1#
#1500000
0#
#1505000
1%
b0 ,
0'
1#
#1510000
0#
#1515000
b10001 "
b10001 )
b0 (
b10001 *
1'
1#
#1520000
0#
#1525000
b11111111111111111111111111111111 ,
0'
1#
#1530000
0#
#1535000
1#
#1540000
0#
#1545000
b111 ,
b10011001 +
1#
#1550000
0#
#1555000
b1 (
b100011 *
1'
1#
#1560000
0#
#1565000
0%
b110 ,
0'
1#
#1570000
0#
#1575000
b10 (
b1000110 *
1'
1#
#1580000
0#
#1585000
b101 ,
0'
1#
#1590000
0#
#1595000
b11 (
b10001100 *
1'
1#
#1600000
0#
#1605000
1!
1%
b100 ,
0'
1#
#1610000
0#
#1615000
b100 (
b11001 *
1'
1#
#1620000
0#
#1625000
0!
b11 ,
0'
1#
#1630000
0#
#1635000
b101 (
b110011 *
1'
1#
#1640000
0#
#1645000
0%
b10 ,
0'
1#
#1650000
0#
#1655000
b110 (
b1100110 *
1'
1#
#1660000
0#
#1665000
b1 ,
0'
1#
#1670000
0#
#1675000
b111 (
b11001100 *
1'
1#
#1680000
0#
#1685000
1!
1%
b0 ,
0'
1#
#1690000
0#
#1695000
b10011001 "
b10011001 )
b0 (
b10011001 *
1'
1#
#1700000
0#
#1705000
b11111111111111111111111111111111 ,
0'
1#
#1710000
0#
#1715000
1#
#1720000
0#
#1725000
0%
b111 ,
b1100110 +
1#
#1730000
0#
#1735000
b1 (
b110010 *
1'
1#
#1740000
0#
#1745000
0!
1%
b110 ,
0'
1#
#1750000
0#
#1755000
b10 (
b1100101 *
1'
1#
#1760000
0#
#1765000
b101 ,
0'
1#
#1770000
0#
#1775000
b11 (
b11001011 *
1'
1#
#1780000
0#
#1785000
1!
0%
b100 ,
0'
1#
#1790000
0#
#1795000
b100 (
b10010110 *
1'
1#
#1800000
0#
#1805000
b11 ,
0'
1#
#1810000
0#
#1815000
b101 (
b101100 *
1'
1#
#1820000
0#
#1825000
0!
1%
b10 ,
0'
1#
#1830000
0#
#1835000
b110 (
b1011001 *
1'
1#
#1840000
0#
#1845000
b1 ,
0'
1#
#1850000
0#
#1855000
b111 (
b10110011 *
1'
1#
#1860000
0#
#1865000
1!
0%
b0 ,
0'
1#
#1870000
0#
#1875000
b1100110 "
b1100110 )
b0 (
b1100110 *
1'
1#
#1880000
0#
#1885000
0!
b11111111111111111111111111111111 ,
0'
1#
#1890000
0#
#1895000
1#
#1900000
0#
#1905000
1%
b111 ,
b11111111 +
1#
#1910000
0#
#1915000
b1 (
b11001101 *
1'
1#
#1920000
0#
#1925000
1!
b110 ,
0'
1#
#1930000
0#
#1935000
b10 (
b10011011 *
1'
1#
#1940000
0#
#1945000
b101 ,
0'
1#
#1950000
0#
#1955000
b11 (
b110111 *
1'
1#
#1960000
0#
#1965000
0!
b100 ,
0'
1#
#1970000
0#
#1975000
b100 (
b1101111 *
1'
1#
#1980000
0#
#1985000
b11 ,
0'
1#
#1990000
0#
#1995000
b101 (
b11011111 *
1'
1#
#2000000
0#
#2005000
1!
b10 ,
0'
1#
#2010000
0#
#2015000
b110 (
b10111111 *
1'
1#
#2020000
0#
#2025000
b1 ,
0'
1#
#2030000
0#
#2035000
b111 (
b1111111 *
1'
1#
#2040000
0#
#2045000
0!
b0 ,
0'
1#
#2050000
0#
#2055000
b11111111 "
b11111111 )
b0 (
b11111111 *
1'
1#
#2060000
0#
#2065000
1!
b11111111111111111111111111111111 ,
0'
1#
